packaged_non_std_code/__init__.py
packaged_non_std_code/ingest_data.py
packaged_non_std_code/score.py
packaged_non_std_code/train.py
packaged_non_std_nisha-0.0.1.dist-info/METADATA
packaged_non_std_nisha-0.0.1.dist-info/WHEEL
packaged_non_std_nisha-0.0.1.dist-info/top_level.txt
packaged_non_std_nisha-0.0.1.dist-info/RECORD
