Metadata-Version: 2.1
Name: packaged_non_std_nisha
Version: 0.0.1
Summary: A custom package for house price prediction
Author-email: Nisha <nisa.ampolu@tigeranalytics.com>
Classifier: Programming Language :: Python :: 3
Classifier: Operating System :: OS Independent
Requires-Python: >=3.8
